TranslatePlus/__init__.py
TranslatePlus/main.py
TranslatePlus-1.0.2.dist-info/LICENSE
TranslatePlus-1.0.2.dist-info/METADATA
TranslatePlus-1.0.2.dist-info/WHEEL
TranslatePlus-1.0.2.dist-info/top_level.txt
TranslatePlus-1.0.2.dist-info/RECORD
